{"uuid": "b7a66b26-e0ab-4533-a404-db2f9afeb3b0", "subject": "sequences_series", "has_image": false, "image": null, "problem": "Suppose that $\\lim_{n \\to \\infty}\\left(\\left|\\frac{ a_{n+1} }{ a_{n} }\\right|\\right)=p$. For which values of $p$ must $\\sum_{n=1}^\\infty\\left(2^n \\cdot a_{n}\\right)$ converge?", "answer": "\\frac{1}{2}"}
{"uuid": "7a75b4a6-486b-4925-b92c-8982e6bc632c", "subject": "sequences_series", "has_image": false, "image": null, "problem": "Find the radius of convergence of the series:\n$$\n\\sum_{k=1}^\\infty \\left(\\frac{ \\left(k!\\right)^3 \\cdot x^k }{ (2 \\cdot k)! }\\right)\n$$", "answer": "0"}
{"uuid": "5eebe4a7-75d3-4e52-913a-54badf5c3c51", "subject": "sequences_series", "has_image": false, "image": null, "problem": "Using the series expansion for the function $(1+x)^m$, calculate approximately $\\sqrt[3]{29}$ with an accuracy of 0.0001.", "answer": "3.0722"}
{"uuid": "ca5ffe7c-f495-43dc-a653-de477cabc185", "subject": "sequences_series", "has_image": false, "image": null, "problem": "Find the radius of convergence of the series:\n$$\n\\sum_{n=1}^\\infty \\left(\\frac{ \\left((2 \\cdot n)!\\right) \\cdot x^n }{ n^{2 \\cdot n} }\\right)\n$$", "answer": "\\frac{e^2}{4}"}
{"uuid": "60a8d80f-c925-47de-9ef0-b9fed3fc658a", "subject": "sequences_series", "has_image": false, "image": null, "problem": "Compute $\\int_{0}^{\\frac{ 1 }{ 3 }} e^{-\\frac{ x^2 }{ 3 }} \\, dx$ with accuracy $0.00001$.", "answer": "0.32926"}
{"uuid": "b775a64a-639f-497b-b064-ba7db40ab3ca", "subject": "sequences_series", "has_image": false, "image": null, "problem": "Using the series expansion for the function $(1+x)^m$, calculate approximately $\\sqrt[3]{7}$ with an accuracy of 0.0001.", "answer": "1.9129"}
{"uuid": "065a1eeb-7581-4b18-bc52-69c80d37e90d", "subject": "sequences_series", "has_image": false, "image": null, "problem": "Use the ratio test to determine the radius of convergence of the series:\n$$\n\\sum_{n=1}^\\infty \\left( \\frac{ (2 \\cdot n)! }{ n^{2 \\cdot n} } \\cdot x^n \\right)\n$$", "answer": "\\frac{e^2}{4}"}
{"uuid": "19e6fecd-10a0-4497-b9dd-72c176820215", "subject": "sequences_series", "has_image": false, "image": null, "problem": "Find the radius of convergence of the series:\n$$\n\\sum_{n=1}^\\infty \\left( \\frac{ \\prod_{i=1}^n(2 \\cdot n) }{ (2 \\cdot n)! } \\cdot x^n \\right)\n$$", "answer": "\\infty"}
{"uuid": "62c22c75-1dc7-4a32-a21b-70f80a9bee23", "subject": "sequences_series", "has_image": false, "image": null, "problem": "Evaluate the integral:\n$$\n\\int_{0}^{\\frac{ 1 }{ 2 }} \\sqrt[5]{1+x^3} \\, dx\n$$\nwith accuracy $\\frac{ 1 }{ 100 }$ using power series expansion.", "answer": "0.503"}
{"uuid": "7888c61c-8515-4146-b87d-2ca3f2030b2c", "subject": "sequences_series", "has_image": false, "image": null, "problem": "Compute $\\sqrt[5]{240}$ with an accuracy of $0.0001$.", "answer": "2.9926"}
{"uuid": "3c515761-f013-4a2c-b5f8-1a70be519118", "subject": "sequences_series", "has_image": false, "image": null, "problem": "Compute $\\sqrt[4]{90}$ with accuracy $0.0001$.", "answer": "3.0801"}
{"uuid": "cb4f082e-28c9-4e3d-bc92-12d111f5c953", "subject": "sequences_series", "has_image": false, "image": null, "problem": "Compute $\\int_{0}^{\\frac{ 1 }{ 5 }} e^{-2 \\cdot x^2} \\, dx$ with accuracy $0.00001$.", "answer": "0.1948"}
{"uuid": "9eee7969-14e8-4e46-af9e-f5abe22824c9", "subject": "sequences_series", "has_image": false, "image": null, "problem": "Let $P_{n}(x)$ be the n-th order Taylor polynomial of $f(x) = \\cos(x)$ about $a = 0$. Find the minimum $n$ such that the approximation $f(x) \\approx P_{n}(x)$ is accurate to within $0.00001$ for every value of $x$ satisfying $|x| \\le 0.1$.", "answer": "3"}
{"uuid": "9e0bf1a0-877c-4582-bfb0-0f1dd3945485", "subject": "sequences_series", "has_image": false, "image": null, "problem": "For a sequence with the general term $x_{n} = \\frac{ 3 \\cdot n - 5 }{ 9 \\cdot n + 4 }$, it is known that $\\lim_{n \\to \\infty} \\left(x_{n}\\right) = \\frac{ 1 }{ 3 }$.\n\nFind the number of points $x_{n}$ lying outside the open interval $\\left(\\frac{ 1 }{ 3 } - \\frac{ 1 }{ 1000 }, \\frac{ 1 }{ 3 } + \\frac{ 1 }{ 1000 }\\right)$.", "answer": "703"}
{"uuid": "cf789d84-24bd-45fa-89da-772ce496d1d0", "subject": "multivariable_calculus", "has_image": false, "image": null, "problem": "Find the measure of the angle $\\theta$ between the three-dimensional vectors $\\vec{a}$ and $\\vec{b}$, expressed in radians rounded to two decimal places, if it is not possible to express it exactly.\n\nGiven:\n$\\vec{a} = 3 \\cdot \\vec{i} - \\vec{j} - 2 \\cdot \\vec{k}$\n$\\vec{b} = \\vec{v} - \\vec{w}$, where $\\vec{v} = 2 \\cdot \\vec{i} + \\vec{j} + 4 \\cdot \\vec{k}$ and $\\vec{w} = 6 \\cdot \\vec{i} + \\vec{j} + 2 \\cdot \\vec{k}$", "answer": "2.84"}
{"uuid": "15780608-0149-4c65-a0bd-fdae388be774", "subject": "multivariable_calculus", "has_image": false, "image": null, "problem": "Find the volume of the solid that lies under the double cone $z^2 = 4 \\cdot x^2 + 4 \\cdot y^2$, inside the cylinder $x^2 + y^2 = x$, and above the plane $z = 0$.", "answer": "\\frac{8}{9}"}
{"uuid": "bcc5b742-cc7b-42d6-98eb-9db904ab8078", "subject": "multivariable_calculus", "has_image": false, "image": null, "problem": "Evaluate $\\int\\int\\int_{E}{\\left(x^3+y^3+z^3\\right) d V}$, where $E$ is the region defined by:\n$$\nE = \\left\\{(x,y,z) | 0 \\le x \\le 2, 0 \\le y \\le 2 \\cdot x, 0 \\le z \\le 4-x-y\\right\\}\n$$", "answer": "\\frac{112}{5}"}
{"uuid": "40a59d5b-7cc2-4527-8be9-d64c434be864", "subject": "multivariable_calculus", "has_image": false, "image": null, "problem": "Evaluate $\\int\\int_{D}{\\left(\\int_{0}^{4 \\cdot x^2+4 \\cdot y^2}{y \\, dz}\\right) \\, dA}$, where $D = \\left\\{(x,y) | x^2+y^2 \\le 4, y \\ge 1, x \\ge 0\\right\\}$ is the projection of $E$ onto the $x \\cdot y$-plane.", "answer": "\\frac{274}{15}"}
{"uuid": "24ca0d32-0edc-4da0-8284-8a9ff5367ce8", "subject": "multivariable_calculus", "has_image": false, "image": null, "problem": "Evaluate the triple integral $\\int_{0}^2 \\int_{4}^6 \\int_{3 \\cdot z}^{3 \\cdot z+2} (5-4 \\cdot y) \\, dx \\, dz \\, dy$ by using the transformation $u=x-3 \\cdot z$, $v=4 \\cdot y$, and $w=z$.", "answer": "8"}
{"uuid": "fe510a69-db18-4182-a55e-c5e84eba20f5", "subject": "multivariable_calculus", "has_image": false, "image": null, "problem": "Calculate the double integral $\\int\\int_{R}{\\left(x^2+y^2\\right) d A}$, where $R$ is the parallelogram with the sides $y=x$, $y=x+2$, $y=2$, and $y=6$.", "answer": "24"}
{"uuid": "91c84b88-d4a5-463f-8f32-094eb4c841e8", "subject": "multivariable_calculus", "has_image": false, "image": null, "problem": "$E$ is located inside the cylinder $x^2+y^2=1$ and between the circular paraboloids $z=1-x^2-y^2$ and $z=x^2+y^2$. Find the volume of $E$.", "answer": "\\frac{\\pi}{4}"}
{"uuid": "1af5b10f-762e-4cf3-a07d-e97b59ef24ed", "subject": "multivariable_calculus", "has_image": false, "image": null, "problem": "Evaluate $\\int\\int\\int_{E}{(2 \\cdot x+5 \\cdot y+7 \\cdot z) d V}$, where $E$ is the region defined by:\n$$\nE = \\left\\{(x,y,z) | 0 \\le x \\le 1, 0 \\le y \\le -x+1, 1 \\le z \\le 2\\right\\}\n$$", "answer": "\\frac{77}{12}"}
{"uuid": "0ad9f006-5f19-45a1-8138-0c9b37517662", "subject": "multivariable_calculus", "has_image": false, "image": null, "problem": "Find the volume of the prism with vertices $A(0,0,0)$, $B(4,0,0)$, $C(4,6,0)$, $D(0,6,0)$, $E(0,0,1)$, and $F(4,0,1)$.", "answer": "12"}
{"uuid": "c1776c95-1585-4f95-8a20-535567d00fae", "subject": "multivariable_calculus", "has_image": false, "image": null, "problem": "Evaluate $\\int\\int\\int_{E}{z \\, dV}$, where $E$ is the region defined by:\n$$\nE = \\left\\{ (x,y,z) \\mid -y \\le x \\le y, \\, 0 \\le y \\le 1, \\, 0 \\le z \\le 1-x^4-y^4 \\right\\}\n$$", "answer": "\\frac{113}{450}"}
{"uuid": "b1d83dc5-da1a-4559-b8f4-c8a0ac9c7e7d", "subject": "multivariable_calculus", "has_image": false, "image": null, "problem": "The integral has been converted to polar coordinates. Verify that the identity is true and choose the easiest way to evaluate the integral, in rectangular or polar coordinates.\n$$\n\\int_{0}^1 \\int_{x^2}^x \\frac{ 1 }{ \\sqrt{x^2+y^2} } \\, dy \\, dx = \\int_{0}^{\\frac{ \\pi }{ 4 }} \\int_{0}^{\\tan(\\varphi) \\cdot \\sec(\\varphi)} 1 \\, dr \\, d \\varphi\n$$", "answer": "\\sqrt{2}-1"}
{"uuid": "6d9acd8c-731d-41f3-b2a6-e84ea4e9f1ac", "subject": "multivariable_calculus", "has_image": false, "image": null, "problem": "Consider points $P(3,7,-2)$ and $Q(1,1,-3)$. Determine the angle between vectors $\\vec{OP}$ and $\\vec{OQ}$. Express the answer in radians, rounded to two decimal places.", "answer": "0.91"}
{"uuid": "04960c86-a731-4641-a3a8-fd0529de5a51", "subject": "multivariable_calculus", "has_image": false, "image": null, "problem": "Evaluate $\\int\\int\\int_{E}{(x+2 \\cdot y \\cdot z) \\, dV}$, where $E = \\left\\{(x,y,z) | 0 \\le x \\le 1, 0 \\le y \\le x, 0 \\le z \\le 5-x-y \\right\\}$.", "answer": "\\frac{439}{120}"}
{"uuid": "cd1538cc-ca04-4235-819e-b0d2b3542eb2", "subject": "algebra", "has_image": false, "image": null, "problem": "The unit price of an item affects its supply and demand. That is, if the unit price goes up, the demand for the item will usually decrease. For example, a local newspaper currently has $84\\ 000$ subscribers at a quarterly charge of $\\$30$. Market research has suggested that if the owners raise the price to $\\$32$, they would lose $5000$ subscribers. Assuming that subscriptions are linearly related to the price, what price should the newspaper charge for a quarterly subscription to maximize their revenue?", "answer": "31.8"}
{"uuid": "bfd92140-56a4-4cd9-a0d4-c99aef34eb24", "subject": "algebra", "has_image": false, "image": null, "problem": "Use the Remainder Theorem to find the remainder when dividing $5 \\cdot x^5 - 4 \\cdot x^4 + 3 \\cdot x^3 - 2 \\cdot x^2 + x - 1$ by $x + 6$.", "answer": "-44791"}
{"uuid": "ea099411-f1fd-44e5-b9db-54271bc9afd6", "subject": "algebra", "has_image": false, "image": null, "problem": "Find an exponential function that passes through the points:\n\n| $x$ | $1$ | $2$ | $3$ | $4$ |\n| --- | --- | --- | --- | --- |\n| $f(x)$ | $10$ | $20$ | $40$ | $80$ |", "answer": "5\\cdot2^x"}
{"uuid": "e09be213-4d6a-4283-860d-c2f57bdaf5d4", "subject": "algebra", "has_image": false, "image": null, "problem": "Let $f(x) = \\frac{ 1 }{ x }$. Find the number $b$ such that the average rate of change of $f$ on the interval $(2,b)$ is $-\\frac{ 1 }{ 10 }$.", "answer": "5"}
{"uuid": "3497d594-978a-4c17-9210-5654e5e7023a", "subject": "algebra", "has_image": false, "image": null, "problem": "The unit price of an item affects its supply and demand. That is, if the unit price goes up, the demand for the item will usually decrease. For example, a local newspaper currently has $84\\ 000$ subscribers at a quarterly charge of $\\$30$. Market research has suggested that if the owners raise the price to $\\$33$, they would lose $7000$ subscribers. Assuming that subscriptions are linearly related to the price, what price should the newspaper charge for a quarterly subscription to maximize their revenue?", "answer": "33"}
{"uuid": "72196b45-ca12-4d25-8f07-dc1dba889917", "subject": "algebra", "has_image": false, "image": null, "problem": "A town has an initial population of $80\\ 000$. It grows at a constant rate of $2200$ per year for $5$ years. The linear function that models the town\u2019s population $P$ as a function of the year is: $P(t) = 80\\ 000 + 2200 \\cdot t$, where $t$ is the number of years since the model began. When will the population reach $120\\ 000$?", "answer": "\\frac{200}{11}"}
{"uuid": "30b1fff3-c7e8-4443-8b21-ad150fba7da0", "subject": "algebra", "has_image": false, "image": null, "problem": "Note that $1 \\in (-3,7)$. Think of the solution of the inequality $|x-1|<\\delta$, where $\\delta$ (delta, a Greek letter) is a constant.\n\nFind the greatest $\\delta$ so that the solution is completely on the interval $(-3,7)$.\n\n[Hint: How far you can go within $(-3,7)$, starting from $1$?]", "answer": "4"}
{"uuid": "b78a35bf-86eb-4ed0-8899-09518687eaeb", "subject": "algebra", "has_image": false, "image": null, "problem": "Use the values of $f(x)$ listed in the table below to solve the equation $f^{-1}(x) = 5$ for $x$.\n\n| $x$ | $0$ | $1$ | $2$ | $3$ | $4$ | $5$ | $6$ | $7$ | $8$ |\n| --- | --- | --- | --- | --- | --- | --- | --- | --- | --- |\n| $f(x)$ | $8$ | $0$ | $7$ | $4$ | $2$ | $6$ | $5$ | $3$ | $9$ |\n\nTo find the solution, we need to find the value of $x$ such that $f(x) = 5$.", "answer": "5"}
{"uuid": "afc947d1-b4ea-4c8e-9540-0fc72f85b060", "subject": "algebra", "has_image": false, "image": null, "problem": "Solve the following equation for $x$:\n\n$3 \\cdot x - (x - 4) = 10 + 5 \\cdot (2 \\cdot x + 2)$", "answer": "-2"}
{"uuid": "80a14173-80b6-4e3b-ace4-a3ff3b2af70e", "subject": "algebra", "has_image": false, "image": null, "problem": "A formula for the normal systolic blood pressure for a man age $A$, measured in mmHg, is given as $P = 0.006 \\cdot A^2 - 0.02 \\cdot A + 120$. Find the age to the nearest year of a man whose normal blood pressure measures $125$ mmHg.", "answer": "31"}
{"uuid": "630ccb25-22c1-49b5-acca-5ee84f2d1f1e", "subject": "algebra", "has_image": false, "image": null, "problem": "For what value of $m$ does the inequality $m \\cdot x + 4 \\le 2 \\cdot x + 5 \\cdot (x - 1)$ have no real solutions?", "answer": "7"}
{"uuid": "92b966b7-4e50-4d96-9376-c3c6dcb81e4c", "subject": "algebra", "has_image": false, "image": null, "problem": "The equation $N(t) = \\frac{ 500 }{ 1+49 \\cdot e^{-0.7 \\cdot t} }$ models the number of people in a town who have heard a rumor after $t$ days. To the nearest whole number, how many people will have heard the rumor after $3$ days?", "answer": "71"}
{"uuid": "6773e6e9-681b-483f-8c75-43833b81fd8a", "subject": "algebra", "has_image": false, "image": null, "problem": "A falling object travels a distance given by the formula $d = 5 \\cdot t + 16 \\cdot t^2$ (ft), where $t$ is measured in seconds. How long will it take for the object to travel $74$ ft?", "answer": "2"}
{"uuid": "a674c2d7-a34b-478c-a2db-568882e13a76", "subject": "integral_calc", "has_image": false, "image": null, "problem": "The chain of length $200$ rises up, winding on the winch. Compute the work of the weight force when lifting the chain, neglecting the size of the winch, if the running meter of the chain weighs $50$ kg.", "answer": "-1000000"}
{"uuid": "531fbc44-4d03-459d-bc47-0dd40bf62702", "subject": "integral_calc", "has_image": false, "image": null, "problem": "Find the area bounded by the curves $y = 3 \\cdot x + 3$, $y = 3 \\cdot \\cos(x)$, and $y = 0$.", "answer": "\\frac{9}{2}"}
{"uuid": "39955d74-b26d-4d7d-ae27-b93ee45f74dc", "subject": "integral_calc", "has_image": false, "image": null, "problem": "Compute the area of the figure bounded by curves $y = 2 \\cdot x^2$, $y = 1 + x^2$, lines $x = 3$, $x = -2$, and the $x$-axis.", "answer": "\\frac{46}{3}"}
{"uuid": "d930869f-c932-4aba-a4ea-e00bc94237a8", "subject": "integral_calc", "has_image": false, "image": null, "problem": "Compute the area of the figure bounded by curves $y = 8 \\cdot x^2$, $y = 4 + 4 \\cdot x^2$, lines $x = 3$, $x = -2$, and the $x$-axis.", "answer": "\\frac{184}{3}"}
{"uuid": "ba021e0e-5fd6-428c-91e4-fcd26bec895f", "subject": "differential_calc", "has_image": false, "image": null, "problem": "Consider a bank investment: The initial investment is $\\$10000$. After $25$ years, the investment has tripled to $\\$30000$. Use Newton\u2019s method to determine the interest rate if the interest was compounded annually.", "answer": "4.492%"}
{"uuid": "b27a2ed1-91ab-4864-b50e-4aebf48d87b1", "subject": "differential_calc", "has_image": false, "image": null, "problem": "Consider a wire 4 ft long cut into two pieces. One piece forms a circle with radius $r$ and the other forms a square of side $x$. Choose $x$ to maximize the sum of their areas.", "answer": "0"}
{"uuid": "337a55dc-e856-4e1e-b717-2c1ca37ca438", "subject": "differential_calc", "has_image": false, "image": null, "problem": "The cost for printing a book can be given by the equation $C(x) = 1000 + 12 \\cdot x + \\frac{ 1 }{ 2 } \\cdot x^{\\frac{ 2 }{ 3 }}$. Use Newton\u2019s method to find the break-even point if the printer sells each book for $\\$20$.", "answer": "127"}
{"uuid": "272ed29b-1de2-48d4-a63d-c8c7173b76ef", "subject": "differential_calc", "has_image": false, "image": null, "problem": "Compute the derivative of the function $f(x) = \\sqrt[x]{3} + \\frac{ 1 }{ 6^{5 \\cdot x} } + 4^{\\sqrt{x}}$ at $x = 1$.", "answer": "-0.5244"}
{"uuid": "b46190d9-ebed-4e4b-b32e-6167579d4c2b", "subject": "differential_calc", "has_image": false, "image": null, "problem": "If it takes $6$ years for an exponentially growing quantity to triple in size, then by what percentage does it increase every year? Round your answer to two decimal places, and omit the % sign.", "answer": "20.09"}
{"uuid": "70ff52a6-d767-4315-9035-91c8cf38c9c5", "subject": "differential_calc", "has_image": false, "image": null, "problem": "Consider a limousine that gets $m(v) = \\frac{ 120-2 \\cdot v }{ 5 }$ mi/gal at speed $v$, the chauffer costs $\\$15$/h, and gas is $\\$3.5$/gal. Find the cheapest driving speed.", "answer": "34.02"}
